explosion/__init__.py
explosion/client.py
explosion-0.0.1.dist-info/LICENSE
explosion-0.0.1.dist-info/METADATA
explosion-0.0.1.dist-info/WHEEL
explosion-0.0.1.dist-info/top_level.txt
explosion-0.0.1.dist-info/RECORD
